FeatureRefiner/__init__.py
FeatureRefiner/create_features.py
FeatureRefiner/date_time_features.py
FeatureRefiner/encoding.py
FeatureRefiner/imputation.py
FeatureRefiner/scaling.py
FeatureRefiner/scripts/app.py
FeatureRefiner/scripts/logo.jpeg
FeatureRefiner/scripts/run_app.py
FeatureRefiner-1.1.dist-info/LICENSE.md
FeatureRefiner-1.1.dist-info/METADATA
FeatureRefiner-1.1.dist-info/WHEEL
FeatureRefiner-1.1.dist-info/entry_points.txt
FeatureRefiner-1.1.dist-info/top_level.txt
FeatureRefiner-1.1.dist-info/RECORD
